{
 "id": 1,
 "body": {
  "part": [
   {
    "id": "CoreComponent",
    "type": "CoreComponent",
    "root": true,
    "orientation": 0
   },
   {
    "id": "myid1000",
    "type": "LightSensor",
    "root": false,
    "orientation": 2
   },
   {
    "id": "myid1001",
    "type": "ActiveHinge",
    "root": false,
    "orientation": 1
   },
   {
    "id": "myid1002",
    "type": "ActiveHinge",
    "root": false,
    "orientation": 1
   },
   {
    "id": "myid1007",
    "type": "FixedBrick",
    "root": false,
    "orientation": 0
   },
   {
    "id": "myid1006",
    "type": "FixedBrick",
    "root": false,
    "orientation": 2
   },
   {
    "id": "myid1004",
    "type": "FixedBrick",
    "root": false,
    "orientation": 2
   },
   {
    "id": "myid1003",
    "type": "LightSensor",
    "root": false,
    "orientation": 0
   },
   {
    "id": "myid1005",
    "type": "LightSensor",
    "root": false,
    "orientation": 0
   }
  ],
  "connection": [
   {
    "src": "CoreComponent",
    "dest": "myid1000",
    "srcSlot": 0,
    "destSlot": 0
   },
   {
    "src": "CoreComponent",
    "dest": "myid1001",
    "srcSlot": 1,
    "destSlot": 0
   },
   {
    "src": "myid1001",
    "dest": "myid1002",
    "srcSlot": 1,
    "destSlot": 0
   },
   {
    "src": "myid1002",
    "dest": "myid1007",
    "srcSlot": 1,
    "destSlot": 0
   },
   {
    "src": "myid1007",
    "dest": "myid1006",
    "srcSlot": 3,
    "destSlot": 0
   },
   {
    "src": "myid1006",
    "dest": "myid1004",
    "srcSlot": 3,
    "destSlot": 0
   },
   {
    "src": "myid1004",
    "dest": "myid1003",
    "srcSlot": 1,
    "destSlot": 0
   },
   {
    "src": "CoreComponent",
    "dest": "myid1005",
    "srcSlot": 3,
    "destSlot": 0
   }
  ]
 },
 "brain": {
  "neuron": [
   {
    "id": "CoreComponent-0",
    "layer": "input",
    "type": "simple",
    "bodyPartId": "CoreComponent",
    "ioId": 0,
    "gain": 1.0
   },
   {
    "id": "CoreComponent-1",
    "layer": "input",
    "type": "simple",
    "bodyPartId": "CoreComponent",
    "ioId": 1,
    "gain": 1.0
   },
   {
    "id": "CoreComponent-2",
    "layer": "input",
    "type": "simple",
    "bodyPartId": "CoreComponent",
    "ioId": 2,
    "gain": 1.0
   },
   {
    "id": "CoreComponent-3",
    "layer": "input",
    "type": "simple",
    "bodyPartId": "CoreComponent",
    "ioId": 3,
    "gain": 1.0
   },
   {
    "id": "CoreComponent-4",
    "layer": "input",
    "type": "simple",
    "bodyPartId": "CoreComponent",
    "ioId": 4,
    "gain": 1.0
   },
   {
    "id": "CoreComponent-5",
    "layer": "input",
    "type": "simple",
    "bodyPartId": "CoreComponent",
    "ioId": 5,
    "gain": 1.0
   },
   {
    "id": "myid1000-0",
    "layer": "input",
    "type": "simple",
    "bodyPartId": "myid1000",
    "ioId": 0,
    "gain": 1.0
   },
   {
    "id": "myid1001-0",
    "layer": "output",
    "type": "sigmoid",
    "bias": -0.75754499435424805,
    "bodyPartId": "myid1001",
    "ioId": 0,
    "gain": 1.0
   },
   {
    "id": "myid1002-0",
    "layer": "output",
    "type": "sigmoid",
    "bias": 1.170770525932312,
    "bodyPartId": "myid1002",
    "ioId": 0,
    "gain": 1.0
   },
   {
    "id": "myid1003-0",
    "layer": "input",
    "type": "simple",
    "bodyPartId": "myid1003",
    "ioId": 0,
    "gain": 1.0
   },
   {
    "id": "myid1005-0",
    "layer": "input",
    "type": "simple",
    "bodyPartId": "myid1005",
    "ioId": 0,
    "gain": 1.0
   }
  ],
  "connection": [
   {
    "src": "CoreComponent-0",
    "dest": "myid1001-0",
    "weight": 0.82482898235321045
   },
   {
    "src": "CoreComponent-0",
    "dest": "myid1002-0",
    "weight": -0.30520865321159363
   },
   {
    "src": "CoreComponent-1",
    "dest": "myid1001-0",
    "weight": -1.1340687274932861
   },
   {
    "src": "CoreComponent-1",
    "dest": "myid1002-0",
    "weight": -0.63983738422393799
   },
   {
    "src": "CoreComponent-2",
    "dest": "myid1001-0",
    "weight": -0.14811500906944275
   },
   {
    "src": "CoreComponent-2",
    "dest": "myid1002-0",
    "weight": -0.31785619258880615
   },
   {
    "src": "CoreComponent-3",
    "dest": "myid1001-0",
    "weight": -1.2318917512893677
   },
   {
    "src": "CoreComponent-3",
    "dest": "myid1002-0",
    "weight": 3.0
   },
   {
    "src": "CoreComponent-4",
    "dest": "myid1001-0",
    "weight": -0.085201837122440338
   },
   {
    "src": "CoreComponent-4",
    "dest": "myid1002-0",
    "weight": 2.8475887775421143
   },
   {
    "src": "CoreComponent-5",
    "dest": "myid1001-0",
    "weight": 2.533463716506958
   },
   {
    "src": "CoreComponent-5",
    "dest": "myid1002-0",
    "weight": 3.0
   },
   {
    "src": "myid1000-0",
    "dest": "myid1001-0",
    "weight": 0.63900572061538696
   },
   {
    "src": "myid1000-0",
    "dest": "myid1002-0",
    "weight": 0.52771943807601929
   },
   {
    "src": "myid1001-0",
    "dest": "myid1001-0",
    "weight": 2.1577117443084717
   },
   {
    "src": "myid1001-0",
    "dest": "myid1002-0",
    "weight": -1.1306003332138062
   },
   {
    "src": "myid1002-0",
    "dest": "myid1001-0",
    "weight": 0.46204662322998047
   },
   {
    "src": "myid1002-0",
    "dest": "myid1002-0",
    "weight": -1.9984022378921509
   },
   {
    "src": "myid1003-0",
    "dest": "myid1001-0",
    "weight": -1.197434663772583
   },
   {
    "src": "myid1003-0",
    "dest": "myid1002-0",
    "weight": 1.9065209627151489
   },
   {
    "src": "myid1005-0",
    "dest": "myid1001-0",
    "weight": 0.50696361064910889
   },
   {
    "src": "myid1005-0",
    "dest": "myid1002-0",
    "weight": 1.6971554756164551
   }
  ]
 }
}